{"serviceUid":"Y80908","runDate":"2019-04-16","serviceType":"train","isPassenger":true,"trainIdentity":"1P36","powerType":"DMU","trainClass":"B","atocCode":"TP","atocName":"Transpennine Express","performanceMonitored":true,"origin":[{"tiploc":"DLTN","description":"Darlington","workingTime":"175100","publicTime":"1751"}],"destination":[{"tiploc":"MNCRIAP","description":"Manchester Airport","workingTime":"200830","publicTime":"2009"}],"locations":[{"realtimeActivated":true,"tiploc":"NWCSTLE","crs":"NCL","description":"Newcastle","gbttBookedDeparture":"1717","origin":[{"tiploc":"DLTN","description":"Darlington","workingTime":"175100","publicTime":"1751"}],"destination":[{"tiploc":"MNCRIAP","description":"Manchester Airport","workingTime":"200830","publicTime":"2009"}],"isCall":true,"isPublicCall":true,"realtimeDeparture":"1717","realtimeDepartureActual":false,"realtimeDepartureNoReport":true,"platform":"10","platformConfirmed":false,"platformChanged":false,"cancelReasonCode":"YI","cancelReasonShortText":"inbound service late","cancelReasonLongText":"late arrival of an inbound service","displayAs":"CANCELLED_CALL"},{"realtimeActivated":true,"tiploc":"CLST","crs":"CLS","description":"Chester-le-Street","gbttBookedArrival":"1726","gbttBookedDeparture":"1726","origin":[{"tiploc":"DLTN","description":"Darlington","workingTime":"175100","publicTime":"1751"}],"destination":[{"tiploc":"MNCRIAP","description":"Manchester Airport","workingTime":"200830","publicTime":"2009"}],"isCall":true,"isPublicCall":true,"realtimeArrival":"1725","realtimeArrivalActual":false,"realtimeArrivalNoReport":true,"realtimeDeparture":"1726","realtimeDepartureActual":false,"realtimeDepartureNoReport":true,"platform":"1","platformConfirmed":false,"platformChanged":false,"cancelReasonCode":"YI","cancelReasonShortText":"inbound service late","cancelReasonLongText":"late arrival of an inbound service","displayAs":"CANCELLED_CALL"},{"realtimeActivated":true,"tiploc":"DRHM","crs":"DHM","description":"Durham","gbttBookedArrival":"1732","gbttBookedDeparture":"1733","origin":[{"tiploc":"DLTN","description":"Darlington","workingTime":"175100","publicTime":"1751"}],"destination":[{"tiploc":"MNCRIAP","description":"Manchester Airport","workingTime":"200830","publicTime":"2009"}],"isCall":true,"isPublicCall":true,"realtimeArrival":"1732","realtimeArrivalActual":false,"realtimeArrivalNoReport":true,"realtimeDeparture":"1733","realtimeDepartureActual":false,"realtimeDepartureNoReport":true,"platform":"1","platformConfirmed":false,"platformChanged":false,"cancelReasonCode":"YI","cancelReasonShortText":"inbound service late","cancelReasonLongText":"late arrival of an inbound service","displayAs":"CANCELLED_CALL"},{"realtimeActivated":true,"tiploc":"DLTN","crs":"DAR","description":"Darlington","gbttBookedArrival":"1750","gbttBookedDeparture":"1751","origin":[{"tiploc":"DLTN","description":"Darlington","workingTime":"175100","publicTime":"1751"}],"destination":[{"tiploc":"MNCRIAP","description":"Manchester Airport","workingTime":"200830","publicTime":"2009"}],"isCall":true,"isPublicCall":true,"realtimeArrival":"1749","realtimeArrivalActual":false,"realtimeArrivalNoReport":true,"realtimeDeparture":"1751","realtimeDepartureActual":true,"platform":"3","platformConfirmed":true,"platformChanged":true,"line":"UM","lineConfirmed":true,"cancelReasonCode":"YI","cancelReasonShortText":"inbound service late","cancelReasonLongText":"late arrival of an inbound service","displayAs":"STARTS"},{"realtimeActivated":true,"tiploc":"YORK","crs":"YRK","description":"York","gbttBookedArrival":"1822","gbttBookedDeparture":"1823","origin":[{"tiploc":"DLTN","description":"Darlington","workingTime":"175100","publicTime":"1751"}],"destination":[{"tiploc":"MNCRIAP","description":"Manchester Airport","workingTime":"200830","publicTime":"2009"}],"isCall":true,"isPublicCall":true,"realtimeArrival":"1822","realtimeArrivalActual":true,"realtimeDeparture":"1823","realtimeDepartureActual":true,"platform":"5","platformConfirmed":true,"platformChanged":false,"line":"UM","lineConfirmed":true,"path":"UF","pathConfirmed":true,"displayAs":"CALL"},{"realtimeActivated":true,"tiploc":"LEEDS","crs":"LDS","description":"Leeds","gbttBookedArrival":"1846","gbttBookedDeparture":"1850","origin":[{"tiploc":"DLTN","description":"Darlington","workingTime":"175100","publicTime":"1751"}],"destination":[{"tiploc":"MNCRIAP","description":"Manchester Airport","workingTime":"200830","publicTime":"2009"}],"isCall":true,"isPublicCall":true,"realtimeArrival":"1848","realtimeArrivalActual":true,"realtimeDeparture":"1849","realtimeDepartureActual":true,"realtimeGbttArrivalLateness":2,"realtimeGbttDepartureLateness":null,"platform":"16","platformConfirmed":true,"platformChanged":false,"line":"F","lineConfirmed":true,"path":"UH","pathConfirmed":true,"displayAs":"CALL"},{"realtimeActivated":true,"tiploc":"HDRSFLD","crs":"HUD","description":"Huddersfield","gbttBookedArrival":"1907","gbttBookedDeparture":"1908","origin":[{"tiploc":"DLTN","description":"Darlington","workingTime":"175100","publicTime":"1751"}],"destination":[{"tiploc":"MNCRIAP","description":"Manchester Airport","workingTime":"200830","publicTime":"2009"}],"isCall":true,"isPublicCall":true,"realtimeArrival":"1907","realtimeArrivalActual":true,"realtimeDeparture":"1908","realtimeDepartureActual":true,"platform":"1","platformConfirmed":true,"platformChanged":false,"line":"UM","lineConfirmed":true,"path":"UHU","pathConfirmed":true,"displayAs":"CALL"},{"realtimeActivated":true,"tiploc":"MNCRVIC","crs":"MCV","description":"Manchester Victoria","gbttBookedArrival":"1938","gbttBookedDeparture":"1940","origin":[{"tiploc":"DLTN","description":"Darlington","workingTime":"175100","publicTime":"1751"}],"destination":[{"tiploc":"MNCRIAP","description":"Manchester Airport","workingTime":"200830","publicTime":"2009"}],"isCall":true,"isPublicCall":true,"realtimeArrival":"1935","realtimeArrivalActual":true,"realtimeDeparture":"1939","realtimeDepartureActual":true,"realtimeGbttArrivalLateness":-2,"realtimeGbttDepartureLateness":null,"platform":"3","platformConfirmed":true,"platformChanged":false,"line":"DSS","lineConfirmed":true,"path":"URS","pathConfirmed":true,"displayAs":"CALL"},{"realtimeActivated":true,"tiploc":"MNCROXR","crs":"MCO","description":"Manchester Oxford Road","gbttBookedArrival":"1945","gbttBookedDeparture":"1947","origin":[{"tiploc":"DLTN","description":"Darlington","workingTime":"175100","publicTime":"1751"}],"destination":[{"tiploc":"MNCRIAP","description":"Manchester Airport","workingTime":"200830","publicTime":"2009"}],"isCall":true,"isPublicCall":true,"realtimeArrival":"1946","realtimeArrivalActual":true,"realtimeDeparture":"1948","realtimeDepartureActual":true,"realtimeGbttArrivalLateness":1,"realtimeGbttDepartureLateness":1,"platform":"4","platformConfirmed":true,"platformChanged":false,"line":"UOX","lineConfirmed":true,"path":"UOX","pathConfirmed":true,"displayAs":"CALL"},{"realtimeActivated":true,"tiploc":"MNCRPIC","crs":"MAN","description":"Manchester Piccadilly","gbttBookedArrival":"1949","gbttBookedDeparture":"1951","origin":[{"tiploc":"DLTN","description":"Darlington","workingTime":"175100","publicTime":"1751"}],"destination":[{"tiploc":"MNCRIAP","description":"Manchester Airport","workingTime":"200830","publicTime":"2009"}],"isCall":true,"isPublicCall":true,"realtimeArrival":"1950","realtimeArrivalActual":true,"realtimeDeparture":"1952","realtimeDepartureActual":true,"realtimeGbttArrivalLateness":1,"realtimeGbttDepartureLateness":1,"platform":"13","platformConfirmed":true,"platformChanged":false,"line":"US","lineConfirmed":true,"path":"UOX","pathConfirmed":true,"displayAs":"CALL"},{"realtimeActivated":true,"tiploc":"MNCRIAP","crs":"MIA","description":"Manchester Airport","gbttBookedArrival":"2009","origin":[{"tiploc":"DLTN","description":"Darlington","workingTime":"175100","publicTime":"1751"}],"destination":[{"tiploc":"MNCRIAP","description":"Manchester Airport","workingTime":"200830","publicTime":"2009"}],"isCall":true,"isPublicCall":true,"realtimeArrival":"2006","realtimeArrivalActual":true,"realtimeGbttArrivalLateness":-2,"platform":"3","platformConfirmed":true,"platformChanged":false,"path":"UA","pathConfirmed":true,"displayAs":"DESTINATION"}],"realtimeActivated":true,"runningIdentity":"1P36"}